__init__.py
__main__.py
drawio2inkscape.py
pdflatex2pdf.py
drawio2pdf/__init__.py
drawio2pdf/__main__.py
drawio2pdf/drawio2inkscape.py
drawio2pdf/pdflatex2pdf.py
drawio2pdf-0.0.0.dist-info/LICENSE
drawio2pdf-0.0.0.dist-info/METADATA
drawio2pdf-0.0.0.dist-info/WHEEL
drawio2pdf-0.0.0.dist-info/entry_points.txt
drawio2pdf-0.0.0.dist-info/top_level.txt
drawio2pdf-0.0.0.dist-info/RECORD
